CONTRIBUTE.rst
LICENSE.txt
MANIFEST.in
README.rst
setup.py
braubuddy/__init__.py
braubuddy/apps.py
braubuddy/runserver.py
braubuddy/utils.py
braubuddy.egg-info/PKG-INFO
braubuddy.egg-info/SOURCES.txt
braubuddy.egg-info/dependency_links.txt
braubuddy.egg-info/entry_points.txt
braubuddy.egg-info/requires.txt
braubuddy.egg-info/top_level.txt
braubuddy/config/api
braubuddy/config/braubuddy
braubuddy/config/dashboard
braubuddy/envcontroller/__init__.py
braubuddy/envcontroller/auto.py
braubuddy/envcontroller/base.py
braubuddy/envcontroller/dummy.py
braubuddy/envcontroller/tosr0x_usb.py
braubuddy/output/__init__.py
braubuddy/output/base.py
braubuddy/output/csvfile.py
braubuddy/output/dweetapi.py
braubuddy/output/graphiteapi.py
braubuddy/output/imagefile.py
braubuddy/output/jsonfile.py
braubuddy/output/libratoapi.py
braubuddy/output/listmemory.py
braubuddy/output/textfile.py
braubuddy/output/twitterapi.py
braubuddy/static/css/bootstrap-theme.min.css
braubuddy/static/css/bootstrap.min.css
braubuddy/static/css/braubuddy.css
braubuddy/static/css/nv.d3.min.css
braubuddy/static/css/weather-icons.min.css
braubuddy/static/fonts/glyphicons-halflings-regular.svg
braubuddy/static/fonts/weathericons-regular-webfont.svg
braubuddy/static/img/favicon.ico
braubuddy/static/js/bootstrap.min.js
braubuddy/static/js/charts.js
braubuddy/static/js/d3.min.js
braubuddy/static/js/jquery-1.11.0.min.js
braubuddy/static/js/nv.d3.min.js
braubuddy/templates/base.html
braubuddy/templates/braubuddy.html
braubuddy/tests/__init__.py
braubuddy/tests/test_utils.py
braubuddy/tests/envcontroller/__init__.py
braubuddy/tests/envcontroller/test_auto.py
braubuddy/tests/envcontroller/test_dummy.py
braubuddy/tests/envcontroller/test_tosr0x_usb.py
braubuddy/tests/output/__init__.py
braubuddy/tests/output/test_csvfile.py
braubuddy/tests/output/test_dweetapi.py
braubuddy/tests/output/test_graphiteapi.py
braubuddy/tests/output/test_imagefile.py
braubuddy/tests/output/test_jsonfile.py
braubuddy/tests/output/test_libratoapi.py
braubuddy/tests/output/test_listmemory.py
braubuddy/tests/output/test_textfile.py
braubuddy/tests/output/test_twitterapi.py
braubuddy/tests/thermometer/__init__.py
